evidence/__init__.py
evidence/schemas.py
evidence/data_sources/__init__.py
evidence/data_sources/base.py
evidence/data_sources/cancer_hotspots.py
evidence/data_sources/cbioportal.py
evidence/dev/README.md
evidence/dev/__init__.py
evidence/dev/cli.py
evidence/dev/etl/__init__.py
evidence/dev/etl/cancer_hotspots.py
evidence/dev/etl/cbioportal.py
evidence_normalizer-0.1.1.dist-info/LICENSE
evidence_normalizer-0.1.1.dist-info/METADATA
evidence_normalizer-0.1.1.dist-info/WHEEL
evidence_normalizer-0.1.1.dist-info/top_level.txt
evidence_normalizer-0.1.1.dist-info/RECORD
