Metadata-Version: 2.2
Name: evidence-normalizer
Version: 0.1.1
Summary: VICC normalization routines for evidence
Author: Alex Wagner, Kori Kuzma, James Stevenson
License: MIT License
Project-URL: Homepage, https://github.com/cancervariants/evidence-normalization
Project-URL: Changelog, https://github.com/cancervariants/evidence-normalization/releases
Project-URL: Source, https://github.com/cancervariants/evidence-normalization
Project-URL: Bug Tracker, https://github.com/cancervariants/evidence-normalization/issues
Classifier: Development Status :: 3 - Alpha
Classifier: Intended Audience :: Science/Research
Classifier: Intended Audience :: Developers
Classifier: Topic :: Scientific/Engineering :: Bio-Informatics
Classifier: License :: OSI Approved :: MIT License
Classifier: Programming Language :: Python :: 3
Classifier: Programming Language :: Python :: 3.11
Classifier: Programming Language :: Python :: 3.12
Classifier: Programming Language :: Python :: 3.13
Requires-Python: >=3.11
License-File: LICENSE
Requires-Dist: pydantic==2.*
Requires-Dist: requests
Requires-Dist: boto3
Provides-Extra: etl
Requires-Dist: variation-normalizer~=0.12.1; extra == "etl"
Requires-Dist: asyncclick; extra == "etl"
Requires-Dist: openpyxl; extra == "etl"
Requires-Dist: pandas; extra == "etl"
Requires-Dist: xlrd; extra == "etl"
Provides-Extra: dev
Requires-Dist: pre-commit>=3.7.1; extra == "dev"
Requires-Dist: ruff==0.5.0; extra == "dev"
Provides-Extra: tests
Requires-Dist: pytest; extra == "tests"
Requires-Dist: pytest-cov; extra == "tests"
